pyisva/__init__.py
pyisva/factory.py
pyisva/core/__init__.py
pyisva/core/accesscontrol.py
pyisva/core/analysisdiagnostics.py
pyisva/core/federationsettings.py
pyisva/core/systemsettings.py
pyisva/core/websettings.py
pyisva/core/access/__init__.py
pyisva/core/access/accesscontrol.py
pyisva/core/access/advancedconfig.py
pyisva/core/access/apiprotection.py
pyisva/core/access/attributes.py
pyisva/core/access/authentication.py
pyisva/core/access/fido2config.py
pyisva/core/access/fido2registrations.py
pyisva/core/access/mappingrules.py
pyisva/core/access/mmfaconfig.py
pyisva/core/access/pip.py
pyisva/core/access/pushnotification.py
pyisva/core/access/riskprofiles.py
pyisva/core/access/runtimeparameters.py
pyisva/core/access/scimconfig.py
pyisva/core/access/serverconnections.py
pyisva/core/access/templatefiles.py
pyisva/core/access/userregistry.py
pyisva/core/analysis/__init__.py
pyisva/core/analysis/applicationlog.py
pyisva/core/federation/__init__.py
pyisva/core/federation/accesspolicy.py
pyisva/core/federation/aliasservice.py
pyisva/core/federation/attributesources.py
pyisva/core/federation/federations.py
pyisva/core/federation/pointofcontact.py
pyisva/core/federation/securitytokenservice.py
pyisva/core/system/__init__.py
pyisva/core/system/adminsettings.py
pyisva/core/system/advancedtuning.py
pyisva/core/system/clicommands.py
pyisva/core/system/cluster.py
pyisva/core/system/configuration.py
pyisva/core/system/datetime.py
pyisva/core/system/dns.py
pyisva/core/system/docker.py
pyisva/core/system/extensions.py
pyisva/core/system/filedownloads.py
pyisva/core/system/fips.py
pyisva/core/system/firststeps.py
pyisva/core/system/fixpacks.py
pyisva/core/system/hostsfile.py
pyisva/core/system/interfaces.py
pyisva/core/system/licensing.py
pyisva/core/system/managementauthorization.py
pyisva/core/system/restartshutdown.py
pyisva/core/system/runtimedb.py
pyisva/core/system/snapshot.py
pyisva/core/system/sslcertificates.py
pyisva/core/system/staticroutes.py
pyisva-0.2.2.dist-info/AUTHORS.md
pyisva-0.2.2.dist-info/LICENSE.txt
pyisva-0.2.2.dist-info/METADATA
pyisva-0.2.2.dist-info/WHEEL
pyisva-0.2.2.dist-info/top_level.txt
pyisva-0.2.2.dist-info/RECORD
