Metadata-Version: 2.1
Name: pyisva
Version: 0.2.2
Summary: Python API for IBM Security Verify Access
Author: Lachlan Gleeson
Author-email: lgleeson@au1.ibm.com
License: MIT
Project-URL: Homepage, https://github.com/lachlan-ibm/pyisva
Project-URL: Documentation, https://lachlan-ibm.github.io/pyisva
Project-URL: Source, https://github.com/lachlan-ibm/pyisva
Project-URL: Tracker, https://github.com/lachlan-ibm/pyisva/issues
License-File: LICENSE.txt
License-File: AUTHORS.md
Requires-Dist: requests
